datamuse/__init__.py
datamuse/annotations.py
datamuse/datamuse.py
datamuse-0.3.0.dist-info/licenses/LICENSE
datamuse-0.3.0.dist-info/METADATA
datamuse-0.3.0.dist-info/WHEEL
datamuse-0.3.0.dist-info/top_level.txt
datamuse-0.3.0.dist-info/RECORD
